simple_toon-0.2.1.dist-info/licenses/LICENSE
toon_parser/__init__.py
toon_parser/advanced.py
toon_parser/io.py
toon_parser/oo_api.py
toon_parser/parser.py
toon_parser/schema.py
toon_parser/serializer.py
toon_parser/streaming.py
simple_toon-0.2.1.dist-info/METADATA
simple_toon-0.2.1.dist-info/WHEEL
simple_toon-0.2.1.dist-info/top_level.txt
simple_toon-0.2.1.dist-info/RECORD
