Metadata-Version: 2.4
Name: simple-toon
Version: 0.2.1
Summary: Python parser and serializer for TOON (Token-Oriented Object Notation) - Reduce LLM token usage by 30-60%
Author-email: Ignac <ignaciocolussi@outlook.com>
Maintainer-email: Ignac <ignaciocolussi@outlook.com>
License: MIT
Project-URL: Homepage, https://github.com/ignaciocolussi/simple_toon
Project-URL: Repository, https://github.com/ignaciocolussi/simple_toon
Project-URL: Documentation, https://github.com/ignaciocolussi/simple_toon#readme
Project-URL: Bug Tracker, https://github.com/ignaciocolussi/simple_toon/issues
Project-URL: Changelog, https://github.com/ignaciocolussi/simple_toon/blob/main/CHANGELOG.md
Keywords: toon,json,parser,serializer,llm,token-optimization,data-format,compression,streaming,schema-validation
Classifier: Development Status :: 4 - Beta
Classifier: Intended Audience :: Developers
Classifier: License :: OSI Approved :: MIT License
Classifier: Operating System :: OS Independent
Classifier: Programming Language :: Python :: 3
Classifier: Programming Language :: Python :: 3.8
Classifier: Programming Language :: Python :: 3.9
Classifier: Programming Language :: Python :: 3.10
Classifier: Programming Language :: Python :: 3.11
Classifier: Programming Language :: Python :: 3.12
Classifier: Programming Language :: Python :: 3 :: Only
Classifier: Topic :: Software Development :: Libraries :: Python Modules
Classifier: Topic :: Text Processing
Classifier: Topic :: Scientific/Engineering :: Artificial Intelligence
Classifier: Typing :: Typed
Requires-Python: >=3.8
License-File: LICENSE
Provides-Extra: dev
Requires-Dist: pytest>=7.4.0; extra == "dev"
Requires-Dist: pytest-cov>=4.1.0; extra == "dev"
Requires-Dist: black>=23.0.0; extra == "dev"
Requires-Dist: ruff>=0.1.0; extra == "dev"
Requires-Dist: mypy>=1.5.0; extra == "dev"
Requires-Dist: build>=1.0.0; extra == "dev"
Requires-Dist: twine>=4.0.0; extra == "dev"
Dynamic: license-file
